geco/__init__.py
geco/generator.py
geco/mips/__init__.py
geco/mips/max_cut.py
geco/mips/packing.py
geco/mips/production_planning.py
geco/mips/scheduling.py
geco/mips/set_packing.py
geco/mips/facility_location/__init__.py
geco/mips/facility_location/cornuejols.py
geco/mips/facility_location/generic.py
geco/mips/facility_location/sun.py
geco/mips/independent_set/__init__.py
geco/mips/independent_set/barabasi_albert.py
geco/mips/independent_set/gasse.py
geco/mips/independent_set/generic.py
geco/mips/independent_set/sun.py
geco/mips/knapsack/__init__.py
geco/mips/knapsack/generic.py
geco/mips/knapsack/pisinger.py
geco/mips/knapsack/yang.py
geco/mips/set_cover/__init__.py
geco/mips/set_cover/generic.py
geco/mips/set_cover/sun.py
geco/mips/set_cover/yang.py
geco/mips/tests/__init__.py
geco/mips/tests/test_facility_location.py
geco/mips/tests/test_independent_set.py
geco/mips/tests/test_knapsack.py
geco/mips/tests/test_max_cut.py
geco/mips/tests/test_packing.py
geco/mips/tests/test_production_planning.py
geco/mips/tests/test_scheduling.py
geco/mips/tests/test_set_cover.py
geco/mips/tests/test_set_packing.py
geco/mips/utilities/__init__.py
geco/mips/utilities/naming.py
geco/tests/__init__.py
geco/tests/test_generator.py
GeCO-0.1.0.dist-info/LICENSE
GeCO-0.1.0.dist-info/METADATA
GeCO-0.1.0.dist-info/WHEEL
GeCO-0.1.0.dist-info/top_level.txt
GeCO-0.1.0.dist-info/RECORD
