Metadata-Version: 2.1
Name: GeCO
Version: 0.1.0
Summary: Generators for Combinatorial Optimization
Home-page: https://github.com/CharJon/GeCO
License: MIT License
Platform: UNKNOWN
Requires-Dist: pyscipopt
Requires-Dist: networkx
Requires-Dist: numpy
